yamlcore/__init__.py
yamlcore/dumper.py
yamlcore/loader.py
yamlcore-0.0.3.dist-info/LICENSE
yamlcore-0.0.3.dist-info/METADATA
yamlcore-0.0.3.dist-info/WHEEL
yamlcore-0.0.3.dist-info/top_level.txt
yamlcore-0.0.3.dist-info/RECORD
