Metadata-Version: 2.1
Name: yamlcore
Version: 0.0.3
Summary: YAML 1.2 Support for PyYAML
Home-page: https://github.com/perlpunk/pyyaml-core
Author: Tina Müller
Author-email: cpan2@tinita.de
Project-URL: Bug Tracker, https://github.com/perlpunk/pyyaml-core/issues
Project-URL: repository, https://github.com/perlpunk/pyyaml-core
Project-URL: changelog, https://github.com/perlpunk/pyyaml-core/blob/main/Changelog.md
Classifier: Programming Language :: Python :: 3
Classifier: License :: OSI Approved :: MIT License
Classifier: Operating System :: OS Independent
Requires-Python: >=3.6
License-File: LICENSE
Requires-Dist: PyYAML
